{
  "id": "features/blender-addon",
  "title": "Blender Addon",
  "description": "The Modelibr Blender addon enables direct integration with your model library, allowing you to browse, import, and upload models without leaving Blender.",
  "source": "@site/docs/features/blender-addon.md",
  "sourceDirName": "features",
  "slug": "/features/blender-addon",
  "permalink": "/features/blender-addon",
  "draft": false,
  "unlisted": false,
  "tags": [],
  "version": "current",
  "sidebarPosition": 4,
  "frontMatter": {
    "sidebar_position": 4
  },
  "sidebar": "tutorialSidebar",
  "previous": {
    "title": "Recycled Files",
    "permalink": "/features/recycled-files"
  },
  "next": {
    "title": "User Interface",
    "permalink": "/features/user-interface"
  }
}